CONTRIBUTING.md
LICENSE
README.md
example.png
setup.py
pdf_diff/__init__.py
pdf_diff/command_line.py
pdf_diff3.egg-info/PKG-INFO
pdf_diff3.egg-info/SOURCES.txt
pdf_diff3.egg-info/dependency_links.txt
pdf_diff3.egg-info/entry_points.txt
pdf_diff3.egg-info/not-zip-safe
pdf_diff3.egg-info/requires.txt
pdf_diff3.egg-info/top_level.txt