Metadata-Version: 1.0
Name: pdf-diff3
Version: 0.9.2
Summary: Finds differences between two PDF documents
Home-page: https://github.com/JoshData/pdf-diff
Author: Joshua Tauberer
Author-email: jt@occams.info
License: CC0 1.0 Universal
Platform: UNKNOWN
